{
    "dataRoles": [
        {
            "displayName": "Rows",
            "name": "rows",
            "kind": "GroupingOrMeasure"
        },
         {
            "displayName": "Other",
            "name": "polarity",
            "kind": "GroupingOrMeasure" 
        },
         {
            "displayName": "Config",
            "name": "config",
            "kind": "GroupingOrMeasure" 
        }       
    ],
    "dataViewMappings": [
        {
            "table": 
                {
                "rows": {
                    "select": [
                        {
                            "for": {
                                "in": "rows"
                            }
                                       
                        },
                        {
                            "for": {
                                "in": "polarity"
                            } 
                        },
                        {
                            "for": {
                                "in": "config"
                            } 
                        }
                    ]
                }
            }
            
            
        }
        
    ],
    "objects": {
        "kPIMeasures": {
            "displayName": "KPI Measure",
            "properties": {
                "collumns":{
                    "displayName": "columns",
                    "type":{
                        "enumeration": [

                        ]
                    }
                },
                "kpi":{
                    "displayName": "KPI",
                    "type": {
                        "enumeration": [
                            {
                                "value": "0",
                                "displayName": ""
                            },
                            {
                                "value": "1",
                                "displayName": "Score"
                            },
                            {
                                "value": "2",
                                "displayName": "Variation"
                            }
                        ]
                    }
                },
                "icon":{
                    "displayName": "icon","suppressFormatPainterCopy": true,
                    "type": {
                        "enumeration": [
                            {
                                "value": "text",
                                "displayName": "Text"
                            },
                            {
                                "value": "bullet",
                                "displayName": "Bullets"
                            },
                            {
                                "value": "arrow",
                                "displayName": "Arrow"
                            }
                        ] 
                    }
                }
            }
        },
        "TableOptions":{
            "displayName": "Table Options",
            "properties": {
                "zoom" :{
                    "displayName": "Zoom",
                    "type": {
                        "formatting": {
                            "fontSize": true
                        }
                    }
                },
                "color":{
                    "displayName": "Color Columns",
                    "type": {
                        "fill": {
                            "solid": {
                                "color":true
                            }
                        }
                    }
                }
            }
        }
    }
}